Workbook

Sheet bank_customers-raw
A1: CustomerID | B1: Age | C1: Gender | D1: Region | E1: EmploymentStatus | F1: AccountType | G1: AccountBalance | H1: MonthlyIncome | I1: CreditScore | J1: LoanAmount | K1: LoanStatus | L1: MonthlyTransactions | M1: DateJoined | N1: Churned
A2: CUS0001 | B2: 56 | C2: Male | D2: Kisumu | E2: Self-Employed | F2: Savings | G2: 36631.49 | H2: 61614.76 | I2: 564 | J2: 64963.66 | K2: Defaulted | L2: 30 | M2: 44410 | N2: No
A3: CUS0002 | B3: 69 | C3: Female | D3: Nairobi | E3: Unemployed | F3: Savings | G3: 67112.82 | H3: 8099.94 | I3: 767 | J3: 246927.03 | K3: Active | L3: 40 | M3: 43329 | N3: No
A4: CUS0003 | B4: 46 | C4: Female | D4: Nairobi | E4: Employed | F4: Savings | G4: 5019 | H4: 47543.97 | I4: 501 | J4: 191289.58 | K4: Active | L4: 46 | M4: 43152 | N4: No
A5: CUS0004 | B5: 32 | C5: Male | D5: Mombasa | E5: Self-Employed | F5: Savings | G5: 39684.55 | H5: 169252.12 | I5: 454 | J5: 46958.25 | K5: Defaulted | L5: 32 | M5: 44619 | N5: No
A6: CUS0005 | B6: 60 | C6: Female | D6: Kisumu | E6: Employed | F6: Current | G6: 159215.69 | H6: 46649.52 | I6: 312 | J6: 45301.24 | K6: Active | L6: 10 | M6: 43664 | N6: No
A7: CUS0006 | B7: 25 | C7: Female | D7: Mombasa | E7: Unemployed | F7: Salary | G7: 122420.84 | H7: 15810.17 | I7: 596 | J7: 75629.84 | K7: Active | L7: 27 | M7: 43602 | N7: No
A8: CUS0007 | B8: 38 | C8: Female | D8: Nairobi | E8: Self-Employed | F8: Savings | G8: 71898.73 | H8: 178648.48 | I8: 797 | J8: 241052.56 | K8: Active | L8: 51 | M8: 43558 | N8: Yes
A9: CUS0008 | B9: 56 | C9: Male | D9: Nakuru | E9: Employed | F9: Savings | G9: 21219.62 | H9: 153074.54 | I9: 544 | J9: 176751.39 | K9: Fully Paid | L9: 8 | M9: 43386 | N9: No
A10: CUS0009 | B10: 36 | C10: Female | D10: Nairobi | E10: Employed | F10: Savings | G10: 25473.31 | H10: 101147.79 | I10: 599 | J10: 166455.65 | K10: Fully Paid | L10: 51 | M10: 44609 | N10: No
A11: CUS0010 | B11: 40 | C11: Female | D11: Eldoret | E11: Employed | F11: Current | G11: 199237.3 | H11: 94853.52 | I11: 661 | J11: 73497.38 | K11: Active | L11: 36 | M11: 43310 | N11: Yes
A12: CUS0011 | B12: 28 | C12: Male | D12: Nairobi | E12: Self-Employed | F12: Savings | G12: 11234.42 | H12: 47498.49 | I12: 653 | J12: 53024.31 | K12: Active | L12: 42 | M12: 44486 | N12: No
A13: CUS0012 | B13: 28 | C13: Male | D13: Kisumu | E13: Employed | F13: Salary | G13: 35292.78 | H13: 119055.45 | I13: 820 | J13: 310412.79 | K13: Fully Paid | L13: 55 | M13: 44617 | N13: No
... A2001: CUS2000 | B2001: 20 | C2001: Male | D2001: Nairobi | E2001: Employed | F2001: Fixed Deposit | G2001: 279469.62 | H2001: 76132.73 | I2001: 743 | J2001: 125786.35 | K2001: Active | L2001: 5 | M2001: 43403 | N2001: No

Sheet Clean Data
A1: CustomerID | B1: Age | C1: Gender | D1: Region | E1: EmploymentStatus | F1: AccountType | G1: AccountBalance | H1: MonthlyIncome | I1: CreditScore | J1: LoanAmount | K1: LoanStatus | L1: MonthlyTransactions | M1: DateJoined | N1: Churned | O1: Loyalty | P1: Age group | Q1: Customer Value | R1: Credit Risk
A2: CUS0001 | B2: 56 | C2: Male | D2: Kisumu | E2: Self-Employed | F2: Savings | G2: 36631.49 | H2: 61614.76 | I2: 564 | J2: 64963.66 | K2: Defaulted | L2: 30 | M2: 44410 | N2: No | O2: {=_xlfn.IFS(L2<=15, "Low Engagement", L2<=35, "Active", L2<=60, "Highly Active", L2>60, "Power User")} -> Active | P2: {=_xlfn.IFS(B2<=25,"Youth",B2<=35,"Young Adult",B2<=50,"Adult",B2<=70,"Senior")} -> Senior | Q2: {=_xlfn.IFS(G2<10000,"Low Value",G2<=50000,"Mid Value",G2<=150000,"High Value",G2>150000,"Premium")} -> Mid Value | R2: {=_xlfn.IFS(I2<500,"High Risk",I2<650,"Medium Risk",I2<750,"Low Risk",I2>=750,"Very Low Risk")} -> Medium Risk
A3: CUS0002 | B3: 69 | C3: Female | D3: Nairobi | E3: Unemployed | F3: Savings | G3: 67112.82 | H3: 8099.94 | I3: 767 | J3: 246927.03 | K3: Active | L3: 40 | M3: 43329 | N3: No | O3: {=_xlfn.IFS(L3<=15, "Low Engagement", L3<=35, "Active", L3<=60, "Highly Active", L3>60, "Power User")} -> Highly Active | P3: {=_xlfn.IFS(B3<=25,"Youth",B3<=35,"Young Adult",B3<=50,"Adult",B3<=70,"Senior")} -> Senior | Q3: {=_xlfn.IFS(G3<10000,"Low Value",G3<=50000,"Mid Value",G3<=150000,"High Value",G3>150000,"Premium")} -> High Value | R3: {=_xlfn.IFS(I3<500,"High Risk",I3<650,"Medium Risk",I3<750,"Low Risk",I3>=750,"Very Low Risk")} -> Very Low Risk
A4: CUS0003 | B4: 46 | C4: Female | D4: Nairobi | E4: Employed | F4: Savings | G4: 5019 | H4: 47543.97 | I4: 501 | J4: 191289.58 | K4: Active | L4: 46 | M4: 43152 | N4: No | O4: {=_xlfn.IFS(L4<=15, "Low Engagement", L4<=35, "Active", L4<=60, "Highly Active", L4>60, "Power User")} -> Highly Active | P4: {=_xlfn.IFS(B4<=25,"Youth",B4<=35,"Young Adult",B4<=50,"Adult",B4<=70,"Senior")} -> Adult | Q4: {=_xlfn.IFS(G4<10000,"Low Value",G4<=50000,"Mid Value",G4<=150000,"High Value",G4>150000,"Premium")} -> Low Value | R4: {=_xlfn.IFS(I4<500,"High Risk",I4<650,"Medium Risk",I4<750,"Low Risk",I4>=750,"Very Low Risk")} -> Medium Risk
A5: CUS0004 | B5: 32 | C5: Male | D5: Mombasa | E5: Self-Employed | F5: Savings | G5: 39684.55 | H5: 169252.12 | I5: 454 | J5: 46958.25 | K5: Defaulted | L5: 32 | M5: 44619 | N5: No | O5: {=_xlfn.IFS(L5<=15, "Low Engagement", L5<=35, "Active", L5<=60, "Highly Active", L5>60, "Power User")} -> Active | P5: {=_xlfn.IFS(B5<=25,"Youth",B5<=35,"Young Adult",B5<=50,"Adult",B5<=70,"Senior")} -> Young Adult | Q5: {=_xlfn.IFS(G5<10000,"Low Value",G5<=50000,"Mid Value",G5<=150000,"High Value",G5>150000,"Premium")} -> Mid Value | R5: {=_xlfn.IFS(I5<500,"High Risk",I5<650,"Medium Risk",I5<750,"Low Risk",I5>=750,"Very Low Risk")} -> High Risk
A6: CUS0005 | B6: 60 | C6: Female | D6: Kisumu | E6: Employed | F6: Current | G6: 159215.69 | H6: 46649.52 | I6: 312 | J6: 45301.24 | K6: Active | L6: 10 | M6: 43664 | N6: No | O6: {=_xlfn.IFS(L6<=15, "Low Engagement", L6<=35, "Active", L6<=60, "Highly Active", L6>60, "Power User")} -> Low Engagement | P6: {=_xlfn.IFS(B6<=25,"Youth",B6<=35,"Young Adult",B6<=50,"Adult",B6<=70,"Senior")} -> Senior | Q6: {=_xlfn.IFS(G6<10000,"Low Value",G6<=50000,"Mid Value",G6<=150000,"High Value",G6>150000,"Premium")} -> Premium | R6: {=_xlfn.IFS(I6<500,"High Risk",I6<650,"Medium Risk",I6<750,"Low Risk",I6>=750,"Very Low Risk")} -> High Risk
A7: CUS0006 | B7: 25 | C7: Female | D7: Mombasa | E7: Unemployed | F7: Salary | G7: 122420.84 | H7: 15810.17 | I7: 596 | J7: 75629.84 | K7: Active | L7: 27 | M7: 43602 | N7: No | O7: {=_xlfn.IFS(L7<=15, "Low Engagement", L7<=35, "Active", L7<=60, "Highly Active", L7>60, "Power User")} -> Active | P7: {=_xlfn.IFS(B7<=25,"Youth",B7<=35,"Young Adult",B7<=50,"Adult",B7<=70,"Senior")} -> Youth | Q7: {=_xlfn.IFS(G7<10000,"Low Value",G7<=50000,"Mid Value",G7<=150000,"High Value",G7>150000,"Premium")} -> High Value | R7: {=_xlfn.IFS(I7<500,"High Risk",I7<650,"Medium Risk",I7<750,"Low Risk",I7>=750,"Very Low Risk")} -> Medium Risk
A8: CUS0007 | B8: 38 | C8: Female | D8: Nairobi | E8: Self-Employed | F8: Savings | G8: 71898.73 | H8: 178648.48 | I8: 797 | J8: 241052.56 | K8: Active | L8: 51 | M8: 43558 | N8: Yes | O8: {=_xlfn.IFS(L8<=15, "Low Engagement", L8<=35, "Active", L8<=60, "Highly Active", L8>60, "Power User")} -> Highly Active | P8: {=_xlfn.IFS(B8<=25,"Youth",B8<=35,"Young Adult",B8<=50,"Adult",B8<=70,"Senior")} -> Adult | Q8: {=_xlfn.IFS(G8<10000,"Low Value",G8<=50000,"Mid Value",G8<=150000,"High Value",G8>150000,"Premium")} -> High Value | R8: {=_xlfn.IFS(I8<500,"High Risk",I8<650,"Medium Risk",I8<750,"Low Risk",I8>=750,"Very Low Risk")} -> Very Low Risk
A9: CUS0008 | B9: 56 | C9: Male | D9: Nakuru | E9: Employed | F9: Savings | G9: 21219.62 | H9: 153074.54 | I9: 544 | J9: 176751.39 | K9: Fully Paid | L9: 8 | M9: 43386 | N9: No | O9: {=_xlfn.IFS(L9<=15, "Low Engagement", L9<=35, "Active", L9<=60, "Highly Active", L9>60, "Power User")} -> Low Engagement | P9: {=_xlfn.IFS(B9<=25,"Youth",B9<=35,"Young Adult",B9<=50,"Adult",B9<=70,"Senior")} -> Senior | Q9: {=_xlfn.IFS(G9<10000,"Low Value",G9<=50000,"Mid Value",G9<=150000,"High Value",G9>150000,"Premium")} -> Mid Value | R9: {=_xlfn.IFS(I9<500,"High Risk",I9<650,"Medium Risk",I9<750,"Low Risk",I9>=750,"Very Low Risk")} -> Medium Risk
A10: CUS0009 | B10: 36 | C10: Female | D10: Nairobi | E10: Employed | F10: Savings | G10: 25473.31 | H10: 101147.79 | I10: 599 | J10: 166455.65 | K10: Fully Paid | L10: 51 | M10: 44609 | N10: No | O10: {=_xlfn.IFS(L10<=15, "Low Engagement", L10<=35, "Active", L10<=60, "Highly Active", L10>60, "Power User")} -> Highly Active | P10: {=_xlfn.IFS(B10<=25,"Youth",B10<=35,"Young Adult",B10<=50,"Adult",B10<=70,"Senior")} -> Adult | Q10: {=_xlfn.IFS(G10<10000,"Low Value",G10<=50000,"Mid Value",G10<=150000,"High Value",G10>150000,"Premium")} -> Mid Value | R10: {=_xlfn.IFS(I10<500,"High Risk",I10<650,"Medium Risk",I10<750,"Low Risk",I10>=750,"Very Low Risk")} -> Medium Risk
A11: CUS0010 | B11: 40 | C11: Female | D11: Eldoret | E11: Employed | F11: Current | G11: 199237.3 | H11: 94853.52 | I11: 661 | J11: 73497.38 | K11: Active | L11: 36 | M11: 43310 | N11: Yes | O11: {=_xlfn.IFS(L11<=15, "Low Engagement", L11<=35, "Active", L11<=60, "Highly Active", L11>60, "Power User")} -> Highly Active | P11: {=_xlfn.IFS(B11<=25,"Youth",B11<=35,"Young Adult",B11<=50,"Adult",B11<=70,"Senior")} -> Adult | Q11: {=_xlfn.IFS(G11<10000,"Low Value",G11<=50000,"Mid Value",G11<=150000,"High Value",G11>150000,"Premium")} -> Premium | R11: {=_xlfn.IFS(I11<500,"High Risk",I11<650,"Medium Risk",I11<750,"Low Risk",I11>=750,"Very Low Risk")} -> Low Risk
A12: CUS0011 | B12: 28 | C12: Male | D12: Nairobi | E12: Self-Employed | F12: Savings | G12: 11234.42 | H12: 47498.49 | I12: 653 | J12: 53024.31 | K12: Active | L12: 42 | M12: 44486 | N12: No | O12: {=_xlfn.IFS(L12<=15, "Low Engagement", L12<=35, "Active", L12<=60, "Highly Active", L12>60, "Power User")} -> Highly Active | P12: {=_xlfn.IFS(B12<=25,"Youth",B12<=35,"Young Adult",B12<=50,"Adult",B12<=70,"Senior")} -> Young Adult | Q12: {=_xlfn.IFS(G12<10000,"Low Value",G12<=50000,"Mid Value",G12<=150000,"High Value",G12>150000,"Premium")} -> Mid Value | R12: {=_xlfn.IFS(I12<500,"High Risk",I12<650,"Medium Risk",I12<750,"Low Risk",I12>=750,"Very Low Risk")} -> Low Risk
A13: CUS0012 | B13: 28 | C13: Male | D13: Kisumu | E13: Employed | F13: Salary | G13: 35292.78 | H13: 119055.45 | I13: 820 | J13: 310412.79 | K13: Fully Paid | L13: 55 | M13: 44617 | N13: No | O13: {=_xlfn.IFS(L13<=15, "Low Engagement", L13<=35, "Active", L13<=60, "Highly Active", L13>60, "Power User")} -> Highly Active | P13: {=_xlfn.IFS(B13<=25,"Youth",B13<=35,"Young Adult",B13<=50,"Adult",B13<=70,"Senior")} -> Young Adult | Q13: {=_xlfn.IFS(G13<10000,"Low Value",G13<=50000,"Mid Value",G13<=150000,"High Value",G13>150000,"Premium")} -> Mid Value | R13: {=_xlfn.IFS(I13<500,"High Risk",I13<650,"Medium Risk",I13<750,"Low Risk",I13>=750,"Very Low Risk")} -> Very Low Risk
... A2001: CUS2000 | B2001: 20 | C2001: Male | D2001: Nairobi | E2001: Employed | F2001: Fixed Deposit | G2001: 279469.62 | H2001: 76132.73 | I2001: 743 | J2001: 125786.35 | K2001: Active | L2001: 5 | M2001: 43403 | N2001: No | O2001: {=_xlfn.IFS(L2001<=15, "Low Engagement", L2001<=35, "Active", L2001<=60, "Highly Active", L2001>60, "Power User")} -> Low Engagement | P2001: {=_xlfn.IFS(B2001<=25,"Youth",B2001<=35,"Young Adult",B2001<=50,"Adult",B2001<=70,"Senior")} -> Youth | Q2001: {=_xlfn.IFS(G2001<10000,"Low Value",G2001<=50000,"Mid Value",G2001<=150000,"High Value",G2001>150000,"Premium")} -> Premium | R2001: {=_xlfn.IFS(I2001<500,"High Risk",I2001<650,"Medium Risk",I2001<750,"Low Risk",I2001>=750,"Very Low Risk")} -> Low Risk

Sheet PT1-Deafult rate by Region
A3: Number of loans | B3: Loan Status
A4: Regions | B4: Active | C4: Defaulted | D4: Fully Paid | E4: Grand Total | F4: Default rate
A5: Eldoret | B5: 64 | C5: 68 | D5: 63 | E5: 195 | F5: =GETPIVOTDATA("CustomerID",$A$3,"Region","Eldoret","LoanStatus","Defaulted")/GETPIVOTDATA("CustomerID",$A$3,"Region","Eldoret") -> 0.34871795
A6: Kisumu | B6: 104 | C6: 107 | D6: 88 | E6: 299 | F6: =GETPIVOTDATA("CustomerID",$A$3,"Region","Kisumu","LoanStatus","Defaulted")/GETPIVOTDATA("CustomerID",$A$3,"Region","Kisumu") -> 0.35785953
A7: Mombasa | B7: 150 | C7: 144 | D7: 129 | E7: 423 | F7: =GETPIVOTDATA("CustomerID",$A$3,"Region","Mombasa","LoanStatus","Defaulted")/GETPIVOTDATA("CustomerID",$A$3,"Region","Mombasa") -> 0.34042553
A8: Nairobi | B8: 263 | C8: 236 | D8: 259 | E8: 758 | F8: =GETPIVOTDATA("CustomerID",$A$3,"Region","Nairobi","LoanStatus","Defaulted")/GETPIVOTDATA("CustomerID",$A$3,"Region","Nairobi") -> 0.31134565
A9: Nakuru | B9: 129 | C9: 99 | D9: 97 | E9: 325 | F9: =GETPIVOTDATA("CustomerID",$A$3,"Region","Nakuru","LoanStatus","Defaulted")/GETPIVOTDATA("CustomerID",$A$3,"Region","Nakuru") -> 0.30461538
A10: Grand Total | B10: 710 | C10: 654 | D10: 636 | E10: 2000 | F10: =GETPIVOTDATA("CustomerID",$A$3,"LoanStatus","Defaulted")/GETPIVOTDATA("CustomerID",$A$3) -> 0.327

Sheet PT2 — Credit Risk vs Loan Defau
A3: Number of loans | B3: Loan status
A4: Credit Risk | B4: Active | C4: Defaulted | D4: Fully Paid | E4: Grand Total | F4: Default Rate
A5: High Risk | B5: 212 | C5: 500 | E5: 712 | F5: =GETPIVOTDATA("CustomerID",$A$3,"LoanStatus","Defaulted","Credit Risk","High Risk")/GETPIVOTDATA("CustomerID",$A$3,"Credit Risk","High Risk") -> 0.70224719
A6: Low Risk | B6: 145 | C6: 40 | D6: 167 | E6: 352 | F6: =GETPIVOTDATA("CustomerID",$A$3,"LoanStatus","Defaulted","Credit Risk","Low Risk")/GETPIVOTDATA("CustomerID",$A$3,"Credit Risk","Low Risk") -> 0.11363636
A7: Medium Risk | B7: 203 | C7: 114 | D7: 239 | E7: 556 | F7: =GETPIVOTDATA("CustomerID",$A$3,"LoanStatus","Defaulted","Credit Risk","Medium Risk")/GETPIVOTDATA("CustomerID",$A$3,"Credit Risk","Medium Risk") -> 0.20503597
A8: Very Low Risk | B8: 150 | D8: 230 | E8: 380 | F8: =GETPIVOTDATA("CustomerID",$A$3,"LoanStatus","Defaulted","Credit Risk","Very Low Risk")/GETPIVOTDATA("CustomerID",$A$3,"Credit Risk","Very Low Risk") -> 0
A9: Grand Total | B9: 710 | C9: 654 | D9: 636 | E9: 2000 | F9: =GETPIVOTDATA("CustomerID",$A$3,"LoanStatus","Defaulted")/GETPIVOTDATA("CustomerID",$A$3) -> 0.327

Sheet PT3-Churn rate by cus value
A3: Count of CustomerID | B3: Churn
A4: Cust Value seg | B4: No | C4: Yes | D4: Grand Total | E4: Churn Rate
A5: High Value | B5: 895 | C5: 159 | D5: 1054 | E5: =GETPIVOTDATA("CustomerID",$A$3,"Churned","Yes","Customer Value","High Value")/GETPIVOTDATA("CustomerID",$A$3,"Customer Value","High Value") -> 0.15085389
A6: Low Value | B6: 72 | C6: 11 | D6: 83 | E6: =GETPIVOTDATA("CustomerID",$A$3,"Churned","Yes","Customer Value","Low Value")/GETPIVOTDATA("CustomerID",$A$3,"Customer Value","Low Value") -> 0.13253012
A7: Mid Value | B7: 405 | C7: 69 | D7: 474 | E7: =GETPIVOTDATA("CustomerID",$A$3,"Churned","Yes","Customer Value","Mid Value")/GETPIVOTDATA("CustomerID",$A$3,"Customer Value","Mid Value") -> 0.14556962
A8: Premium | B8: 329 | C8: 60 | D8: 389 | E8: =GETPIVOTDATA("CustomerID",$A$3,"Churned","Yes","Customer Value","Premium")/GETPIVOTDATA("CustomerID",$A$3,"Customer Value","Premium") -> 0.15424165
A9: Grand Total | B9: 1701 | C9: 299 | D9: 2000 | E9: =GETPIVOTDATA("CustomerID",$A$3,"Churned","Yes")/GETPIVOTDATA("CustomerID",$A$3) -> 0.1495

Sheet PT4 — Average Balance by Region
A3: Average of AccountBalance | B3: Account type
A4: Regions | B4: Current | C4: Fixed Deposit | D4: Salary | E4: Savings | F4: Grand Total
A5: Eldoret | B5: 82749.025 | C5: 280812.38 | D5: 71944.768 | E5: 48885.042 | F5: 97510.977
A6: Kisumu | B6: 110730.81 | C6: 260047.73 | D6: 81515.083 | E6: 50244.983 | F6: 107374.98
A7: Mombasa | B7: 109409.91 | C7: 256139.54 | D7: 81183.407 | E7: 52559.236 | F7: 112328.32
A8: Nairobi | B8: 103270.89 | C8: 276710.07 | D8: 82530.833 | E8: 51532.299 | F8: 106223.82
A9: Nakuru | B9: 104156.7 | C9: 249034.75 | D9: 78005.708 | E9: 51273.197 | F9: 110378.76
A10: Grand Total | B10: 103622.46 | C10: 264510.47 | D10: 80324.901 | E10: 51238.948 | F10: 107512.7

Sheet PT5-Employment v Default Rate
A3: Loan Count | B3: Loan Status
A4: Employment Status | B4: Active | C4: Defaulted | D4: Fully Paid | E4: Grand Total | F4: Default Rate
A5: Employed | B5: 344 | C5: 310 | D5: 279 | E5: 933 | F5: =GETPIVOTDATA("CustomerID",$A$3,"EmploymentStatus","Employed","LoanStatus","Defaulted")/GETPIVOTDATA("CustomerID",$A$3,"EmploymentStatus","Employed") -> 0.33226152
A6: Self-Employed | B6: 211 | C6: 195 | D6: 197 | E6: 603 | F6: =GETPIVOTDATA("CustomerID",$A$3,"EmploymentStatus","Self-Employed","LoanStatus","Defaulted")/GETPIVOTDATA("CustomerID",$A$3,"EmploymentStatus","Self-Employed") -> 0.32338308
A7: Student | B7: 52 | C7: 65 | D7: 63 | E7: 180 | F7: =GETPIVOTDATA("CustomerID",$A$3,"EmploymentStatus","Student","LoanStatus","Defaulted")/GETPIVOTDATA("CustomerID",$A$3,"EmploymentStatus","Student") -> 0.36111111
A8: Unemployed | B8: 103 | C8: 84 | D8: 97 | E8: 284 | F8: =GETPIVOTDATA("CustomerID",$A$3,"EmploymentStatus","Unemployed","LoanStatus","Defaulted")/GETPIVOTDATA("CustomerID",$A$3,"EmploymentStatus","Unemployed") -> 0.29577465
A9: Grand Total | B9: 710 | C9: 654 | D9: 636 | E9: 2000 | F9: =GETPIVOTDATA("CustomerID",$A$3,"LoanStatus","Defaulted")/GETPIVOTDATA("CustomerID",$A$3) -> 0.327

Sheet Formula Analysis
A1: COUNTIF
A2: Question | B2: Excel Formula
A3: How many High Risk customers have Defaulted? | B3: =COUNTIFS('Clean Data'!R:R,"*High Risk*",'Clean Data'!K:K,"*Defaulted*") -> 500
A4: How many Premium customers have Churned? | B4: =COUNTIFS('Clean Data'!Q:Q,'Clean Data'!Q1975,'Clean Data'!N:N,'Clean Data'!N1981) -> 60
A5: How many Employed customers are High Risk? | B5: =COUNTIFS('Clean Data'!E:E,"Employed",'Clean Data'!R:R,"High Risk") -> 337
A6: How many Nairobi customers have Active loans? | B6: =COUNTIFS('Clean Data'!D:D,"Nairobi",'Clean Data'!K:K,"Active") -> 263
A8: AVEREGE IF
A9: Question | B9: Formulated Results
A10: Average balance of High Risk Defaulted customers | B10: =AVERAGEIFS('Clean Data'!G:G,'Clean Data'!R:R,"High Risk",'Clean Data'!K:K,"Defaulted") -> 102989.93
A11: Average balance of Premium customers who Churned | B11: =AVERAGEIFS('Clean Data'!G:G,'Clean Data'!Q:Q,"Premium",'Clean Data'!N:N,"Yes") -> 230258.43
A12: Average income of Employed customers in Nairobi | B12: =AVERAGEIFS('Clean Data'!H:H,'Clean Data'!E:E,"Employed",'Clean Data'!D:D,"Nairobi") -> 118715.68
A13: Average credit score of Defaulted customers | B13: =AVERAGEIFS('Clean Data'!I:I,'Clean Data'!K:K,"Defaulted") -> 450.20336
A14: Average loan of Unemployed customers who Defaulted | B14: =AVERAGEIFS('Clean Data'!J:J,'Clean Data'!E:E,"Unemployed",'Clean Data'!K:K,"Defaulted") -> 39993.553

Sheet Key Findings
A2: Key Findings & Business Implications | E2: Risk Management & Default Analysis
A4: Finding | B4: Business Implication | D4: Finding | E4: Business Implication
A5: Churn rate is flat at 15% across all value segments | B5: Churn is service-driven not balance-driven — review customer experience | D5: Overall default rate is 33% | E5: 1 in 3 loans defaults — urgent risk management review needed
A6: Overall churn rate of 15% exceeds industry benchmark | B6: Urgent retention strategy needed across all segments | D6: Kisumu has highest regional default rate at 36% | E6: Monitor regional lending in Kisumu and Eldoret
A7: Mombasa has highest average customer balance | B7: High value market despite smaller customer base | D7: Regional default rates vary by only 6% | E7: Default risk is customer-driven not geography-driven
A8: Fixed Deposit holds highest average balances | B8: Promote Fixed Deposit products to grow high-balance customer base
A10: Demographic Risk Findings | E10: Finding | F10: Business Implication
E11: High Risk defaulters hold avg KES 102,990 balance | F11: Structure loan repayments against existing balances for High Risk borrowers
B12: Finding | C12: Business Implication | E12: 60 Premium customers churned — avg balance KES 230,258 | F12: Approx KES 13.8M in lost deposits — urgent Premium retention programme needed
B13: Students have the highest loan default rate | C13: Review student loan products — consider income-based repayment structures or guarantor requirements | E13: Average credit score of defaulters is 450 — High Risk band | F13: Credit score validated as primary loan approval criterion
B14: Unemployed customers default less than students | C14: Loan approval filters for unemployed customers may be effectively screening high-risk borrowers | E14: Employed customers in Nairobi earn avg KES 118,716 | F14: Prime target segment for premium banking products and higher loan limits
B16: FINDINGS SUMMARY
A17: Category | B17: Finding | C17: Business Implication
A18: Risk | B18: Overall default rate is 33%. | C18: Urgent risk management review needed.
A19: Risk | B19: Kisumu has the highest default rate (36%). | C19: Monitor lending strictly in Kisumu and Eldoret.
A20: Risk | B20: High Risk customers default at 70%. | C20: Immediate review of lending policy for High Risk segments.
A21: Risk | B21: Average credit score of defaulters is 450. | C21: Credit score validated as the primary approval criterion.
A22: Risk | B22: Students have the highest default rate (36%). | C22: Review and tighten student loan product requirements.
A23: Growth | B23: Mombasa has the highest overall average balance. | C23: High-value market; prioritize premium growth here.
A24: Growth | B24: Fixed Deposits hold KES 87.3M total deposits. | C24: Most valuable product; prioritize asset growth here.
A25: Growth | B25: Eldoret Fixed Deposits have the highest avg balance. | C25: Expand Fixed Deposit marketing presence in Eldoret.
A26: Growth | B26: Employed Nairobi customers earn avg KES 118,716. | C26: Prime target segment for premium product cross-selling.
A27: Retention | B27: 60 Premium customers churned (Avg KES 230,258). | C27: KES 13.8M in lost deposits; urgent retention action needed.
A28: Retention | B28: Churn rate is flat at 15% across all segments. | C28: Churn is service-driven, not balance or value-driven.
... A37: Integrity | B37: SQL validated all Excel findings. | C37: Analysis integrity confirmed across two separate tools.
